{
	"entityTableList": [{
		"tableName": "Aml_Grade_Weight",
		"autoGenerateId": false,
		"idColumnSet": ["subitem_no"],
		"entityColumnList": [{
			"columnType": "string",
			"columnDescription": "子项类别",
			"columnName": "subitem_category",
			"showColumn": "const:sys_050"
		}, {
			"columnType": "string",
			"columnDescription": "子项编号",
			"columnName": "subitem_no"
		}, {
			"columnType": "string",
			"columnDescription": "子项名称",
			"columnName": "subitem_name"
		}, {
			"columnType": "string",
			"columnDescription": "客户类型",
			"columnName": "customer_type",
			"showColumn": "const:sys_036"
		}, {
			"columnType": "string",
			"columnDescription": "子项默认分数",
			"columnName": "subitem_score"
		}, {
			"columnType": "string",
			"columnDescription": "子项权重",
			"columnName": "subitem_weight"
		}],
		"dataSourceName": "",
		"logicIdColumnSet": []
	}, {
		"tableName": "Aml_Grade_Score",
		"autoGenerateId": true,
		"idColumnSet": ["auto_id"],
		"entityColumnList": [{
			"columnType": "string",
			"columnDescription": "主键",
			"columnName": "auto_id"
		}, {
			"columnType": "string",
			"columnDescription": "分类标识",
			"columnName": "category"
		}, {
			"columnType": "string",
			"columnDescription": "值域",
			"columnName": "value"
		}, {
			"columnType": "string",
			"columnDescription": "分数",
			"columnName": "score"
		}, {
			"columnType": "string",
			"columnDescription": "评级子项",
			"columnName": "subitem_nos"
		}],
		"dataSourceName": "",
		"logicIdColumnSet": [],
		"keyNameColumnList": ["category", "value"]
	}, {
		"tableName": "aml_cust_risk_data",
		"autoGenerateId": true,
		"idColumnSet": ["auto_id"],
		"entityColumnList": [{
			"columnType": "string",
			"columnDescription": "主键",
			"columnName": "auto_id"
		}, {
			"columnType": "string",
			"columnDescription": "",
			"columnName": "cols_name"
		}, {
			"columnType": "string",
			"columnDescription": "",
			"columnName": "cols_isnull"
		}, {
			"columnType": "string",
			"columnDescription": "",
			"columnName": "table_name"
		}],
		"dataSourceName": "",
		"logicIdColumnSet": [],
		"keyNameColumnList": []
	}, {
		"tableName": "aml_cust_risk_cols",
		"autoGenerateId": true,
		"idColumnSet": ["auto_id"],
		"entityColumnList": [{
			"columnType": "string",
			"columnDescription": "主键",
			"columnName": "auto_id"
		}, {
			"columnType": "string",
			"columnDescription": "",
			"columnName": "cols_name"
		}, {
			"columnType": "string",
			"columnDescription": "",
			"columnName": "cols_remarks"
		}, {
			"columnType": "string",
			"columnDescription": "",
			"columnName": "cols_isnull"
		}, {
			"columnType": "string",
			"columnDescription": "",
			"columnName": "table_name"
		}],
		"dataSourceName": "",
		"logicIdColumnSet": [],
		"keyNameColumnList": []
	}, {
		"tableName": "aml_cust_susdata",
		"autoGenerateId": true,
		"idColumnSet": ["auto_id"],
		"entityColumnList": [{
			"columnType": "string",
			"columnDescription": "主键",
			"columnName": "auto_id"
		}, {
			"columnType": "date",
			"columnDescription": "",
			"columnName": "date_id"
		}, {
			"columnType": "string",
			"columnDescription": "",
			"columnName": "customer_no"
		}, {
			"columnType": "string",
			"columnDescription": "",
			"columnName": "customer_type"
		}, {
			"columnType": "string",
			"columnDescription": "",
			"columnName": "suscount"
		}, {
			"columnType": "string",
			"columnDescription": "",
			"columnName": "blackcount"
		}],
		"dataSourceName": "",
		"logicIdColumnSet": [],
		"keyNameColumnList": []
	}, {
		"tableName": "aml_risk_cust",
		"autoGenerateId": true,
		"idColumnSet": ["auto_id"],
		"entityColumnList": [{
			"columnType": "string",
			"columnDescription": "主键",
			"columnName": "auto_id"
		}, {
			"columnType": "string",
			"columnDescription": "",
			"columnName": "customer_type"
		}, {
			"columnType": "string",
			"columnDescription": "",
			"columnName": "customer_no"
		}],
		"dataSourceName": "",
		"logicIdColumnSet": [],
		"keyNameColumnList": []
	}]
}